ZEMO/__init__.py
ZEMO/dataset.py
ZEMO/zemo.py
ZEMO-1.0.0.dist-info/LICENSE
ZEMO-1.0.0.dist-info/METADATA
ZEMO-1.0.0.dist-info/WHEEL
ZEMO-1.0.0.dist-info/top_level.txt
ZEMO-1.0.0.dist-info/RECORD
