Metadata-Version: 2.1
Name: ZEMO
Version: 1.0.0
Summary: Zernike moments: Digital images
Author-email: Hossein Safari <safari@znu.ac.ir>, Nasibe Alipour <nasibealipour@gmail.com>, Hamed Ghaderi <albert.ghaderi@gmail.com>
Project-URL: Homepage, https://github.com/hmddev1/ZM
Classifier: Programming Language :: Python :: 3
Classifier: License :: OSI Approved :: MIT License
Classifier: Operating System :: OS Independent
Requires-Python: >=3.8
License-File: LICENSE
